example_package/__init__.py
example_package/example.py
Maks228-0.2.0.dist-info/LICENSE.txt
Maks228-0.2.0.dist-info/METADATA
Maks228-0.2.0.dist-info/WHEEL
Maks228-0.2.0.dist-info/top_level.txt
Maks228-0.2.0.dist-info/RECORD
