Metadata-Version: 2.1
Name: Maks228
Version: 0.2.0
Summary: test
Home-page: https://github.com/pypa/sampleproject
Author: Maks 4 class
Author-email: nmaks6381@gmail.com
License: UNKNOWN
Project-URL: Bug Tracker, https://github.com/pypa/sampleproject/issues
Platform: UNKNOWN
Classifier: Programming Language :: Python :: 3
Classifier: License :: OSI Approved :: MIT License
Classifier: Operating System :: OS Independent
Requires-Python: >=3.6
License-File: LICENSE.txt
